Workbook

Sheet Sheet1
A1: pos | B1: upos | C1: lemma | D1: senseID | E1: definition | F1: literals | G1: domain | H1: source | I1: Type | J1: Dužina | L1: Akcija
A2: N | B2: NOUN | C2: atomski radjus | D2: LLM-0009 | E2: udaljenost od jezgra atoma do njegove spoljne elektronske ljuske. | H2: ChatGPT 4.5 | I2: NID | J2: =len(E2) -> 65 | K2: =D2&C2 -> LLM-0009atomski radjus | L2: =ifna(VLOOKUP(K2,'Лист1'!D:E,2,false))
A3: N | B3: NOUN | C3: beli pirinač | D3: LLM-0015 | E3: pirinač sa koga su uklonjene spoljašnje ljuske i klica, čime gubi deo hranljivih sastojaka, ali ima duži rok trajanja. | H3: ChatGPT 4.5 | I3: NID | J3: =len(E3) -> 118 | K3: =D3&C3 -> LLM-0015beli pirinač | L3: =ifna(VLOOKUP(K3,'Лист1'!D:E,2,false))
A4: V | B4: VERB | C4: biti u nečijim rukama | D4: LLM-0020 | E4: biti pod nečijom kontrolom. | H4: ChatGPT 4.5 | I4: VID | J4: =len(E4) -> 27 | K4: =D4&C4 -> LLM-0020biti u nečijim rukama | L4: =ifna(VLOOKUP(K4,'Лист1'!D:E,2,false))
A5: V | B5: VERB | C5: biti u rukama | D5: LLM-0020 | E5: biti pod nečijom kontrolom. | H5: ChatGPT 4.5 | I5: VID | J5: =len(E5) -> 27 | K5: =D5&C5 -> LLM-0020biti u rukama | L5: =ifna(VLOOKUP(K5,'Лист1'!D:E,2,false))
A6: N | B6: NOUN | C6: devizni kurs | D6: LLM-0029 | E6: vrednost jedne valute izražena u drugoj valuti | H6: ChatGPT 4.5 | I6: NID | J6: =len(E6) -> 46 | K6: =D6&C6 -> LLM-0029devizni kurs | L6: =ifna(VLOOKUP(K6,'Лист1'!D:E,2,false))
A7: N | B7: NOUN | C7: društvena mreža | D7: LLM-0039 | E7: digitalna platforma za povezivanje, komunikaciju i interakciju između korisnika. | H7: ChatGPT 4.5 | I7: NID | J7: =len(E7) -> 80 | K7: =D7&C7 -> LLM-0039društvena mreža | L7: =ifna(VLOOKUP(K7,'Лист1'!D:E,2,false))
A8: N | B8: NOUN | C8: državne granice | D8: LLM-0042 | E8: teritorijalne granice kojima država definiše svoju jurisdikciju. | H8: ChatGPT 4.5 | I8: NID | J8: =len(E8) -> 64 | K8: =D8&C8 -> LLM-0042državne granice | L8: =ifna(VLOOKUP(K8,'Лист1'!D:E,2,false))
A9: N | B9: NOUN | C9: geografski položaj | D9: LLM-0057 | E9: lokacija nekog mesta određena geografskim koordinatama. | H9: ChatGPT 4.5 | I9: NID | J9: =len(E9) -> 55 | K9: =D9&C9 -> LLM-0057geografski položaj | L9: =ifna(VLOOKUP(K9,'Лист1'!D:E,2,false))
A10: N | B10: NOUN | C10: gravitacioni bunar | D10: LLM-0058 | E10: metaforični opis gravitacionog polja oko masivnog tela iz kojeg je potrebna energija za izlazak. | H10: ChatGPT 4.5 | I10: NID | J10: =len(E10) -> 96 | K10: =D10&C10 -> LLM-0058gravitacioni bunar | L10: =ifna(VLOOKUP(K10,'Лист1'!D:E,2,false))
A11: V | B11: VERB | C11: ima uticaj | D11: LLM-0068 | E11: odrednica: imati uticaj; delovati, uticati na nekoga ili nešto | H11: ChatGPT 4.5 | I11: LVC.full | J11: =len(E11) -> 62 | K11: =D11&C11 -> LLM-0068ima uticaj | L11: =ifna(VLOOKUP(K11,'Лист1'!D:E,2,false))
A12: N | B12: NOUN | C12: industrijska revolucija | D12: LLM-0072 | E12: istorijski period intenzivne industrijalizacije, posebno od kraja 18. do sredine 19. veka. | H12: ChatGPT 4.5 | I12: NID | J12: =len(E12) -> 90 | K12: =D12&C12 -> LLM-0072industrijska revolucija | L12: =ifna(VLOOKUP(K12,'Лист1'!D:E,2,false))
A13: N | B13: NOUN | C13: informaciona tehnologija | D13: LLM-0073 | E13: oblast koja se bavi primenom računara i softvera za upravljanje informacijama. | H13: ChatGPT 4.5 | I13: NID | J13: =len(E13) -> 78 | K13: =D13&C13 -> LLM-0073informaciona tehnologija | L13: =ifna(VLOOKUP(K13,'Лист1'!D:E,2,false))
... A227: A | B227: ADJ | C227: Zamljin | D227: CVDf-397/0 | E227: prisvojni pridev od Zamlja | H227: Cvetana | I227: S | J227: =len(E227) -> 26 | K227: =D227&C227 -> CVDf-397/0Zamljin | L227: =ifna(VLOOKUP(K227,'Лист1'!D:E,2,false))
A228: RN | B228: ADJ | C228: 1. | D228: CVDf-398/1 | E228: ="redni broj od kardinalnog broja " & substitute(C228,".","") -> redni broj od kardinalnog broja 1 | H228: Cvetana | I228: S | J228: =len(E228) -> 33 | K228: =D228&C228 -> CVDf-398/11. | L228: =ifna(VLOOKUP(K228,'Лист1'!D:E,2,false))
A229: RN | B229: ADJ | C229: 10. | D229: ="CVDf-"& mid(D228,6,3)+1 &"/1" -> CVDf-399/1 | E229: ="redni broj od kardinalnog broja " & substitute(C229,".","") -> redni broj od kardinalnog broja 10 | H229: Cvetana | I229: S | J229: =len(E229) -> 34 | K229: =D229&C229 -> CVDf-399/110. | L229: =ifna(VLOOKUP(K229,'Лист1'!D:E,2,false))
A230: RN | B230: ADJ | C230: 1014. | D230: ="CVDf-"& mid(D229,6,3)+1 &"/1" -> CVDf-400/1 | E230: ="redni broj od kardinalnog broja " & substitute(C230,".","") -> redni broj od kardinalnog broja 1014 | H230: Cvetana | I230: S | J230: =len(E230) -> 36 | K230: =D230&C230 -> CVDf-400/11014. | L230: =ifna(VLOOKUP(K230,'Лист1'!D:E,2,false))
A231: RN | B231: ADJ | C231: 1030. | D231: ="CVDf-"& mid(D230,6,3)+1 &"/1" -> CVDf-401/1 | E231: ="redni broj od kardinalnog broja " & substitute(C231,".","") -> redni broj od kardinalnog broja 1030 | H231: Cvetana | I231: S | J231: =len(E231) -> 36 | K231: =D231&C231 -> CVDf-401/11030. | L231: =ifna(VLOOKUP(K231,'Лист1'!D:E,2,false))
A232: RN | B232: ADJ | C232: 1066. | D232: ="CVDf-"& mid(D231,6,3)+1 &"/1" -> CVDf-402/1 | E232: ="redni broj od kardinalnog broja " & substitute(C232,".","") -> redni broj od kardinalnog broja 1066 | H232: Cvetana | I232: S | J232: =len(E232) -> 36 | K232: =D232&C232 -> CVDf-402/11066. | L232: =ifna(VLOOKUP(K232,'Лист1'!D:E,2,false))
A233: RN | B233: ADJ | C233: 1088. | D233: ="CVDf-"& mid(D232,6,3)+1 &"/1" -> CVDf-403/1 | E233: ="redni broj od kardinalnog broja " & substitute(C233,".","") -> redni broj od kardinalnog broja 1088 | H233: Cvetana | I233: S | J233: =len(E233) -> 36 | K233: =D233&C233 -> CVDf-403/11088. | L233: =ifna(VLOOKUP(K233,'Лист1'!D:E,2,false))
A234: RN | B234: ADJ | C234: 1093 | D234: ="CVDf-"& mid(D233,6,3)+1 &"/1" -> CVDf-404/1 | E234: ="redni broj od kardinalnog broja " & substitute(C234,".","") -> redni broj od kardinalnog broja 1093 | H234: Cvetana | I234: S | J234: =len(E234) -> 36 | K234: =D234&C234 -> CVDf-404/11093 | L234: =ifna(VLOOKUP(K234,'Лист1'!D:E,2,false))
A235: RN | B235: ADJ | C235: 1095. | D235: ="CVDf-"& mid(D234,6,3)+1 &"/1" -> CVDf-405/1 | E235: ="redni broj od kardinalnog broja " & substitute(C235,".","") -> redni broj od kardinalnog broja 1095 | H235: Cvetana | I235: S | J235: =len(E235) -> 36 | K235: =D235&C235 -> CVDf-405/11095. | L235: =ifna(VLOOKUP(K235,'Лист1'!D:E,2,false))
A236: RN | B236: ADJ | C236: 1099. | D236: ="CVDf-"& mid(D235,6,3)+1 &"/1" -> CVDf-406/1 | E236: ="redni broj od kardinalnog broja " & substitute(C236,".","") -> redni broj od kardinalnog broja 1099 | H236: Cvetana | I236: S | J236: =len(E236) -> 36 | K236: =D236&C236 -> CVDf-406/11099. | L236: =ifna(VLOOKUP(K236,'Лист1'!D:E,2,false))
A237: RN | B237: ADJ | C237: 11. | D237: ="CVDf-"& mid(D236,6,3)+1 &"/1" -> CVDf-407/1 | E237: ="redni broj od kardinalnog broja " & substitute(C237,".","") -> redni broj od kardinalnog broja 11 | H237: Cvetana | I237: S | J237: =len(E237) -> 34 | K237: =D237&C237 -> CVDf-407/111. | L237: =ifna(VLOOKUP(K237,'Лист1'!D:E,2,false))
A238: RN | B238: ADJ | C238: 1100. | D238: ="CVDf-"& mid(D237,6,3)+1 &"/1" -> CVDf-408/1 | E238: ="redni broj od kardinalnog broja " & substitute(C238,".","") -> redni broj od kardinalnog broja 1100 | H238: Cvetana | I238: S | J238: =len(E238) -> 36 | K238: =D238&C238 -> CVDf-408/11100. | L238: =ifna(VLOOKUP(K238,'Лист1'!D:E,2,false))
A239: RN | B239: ADJ | C239: 1107. | D239: ="CVDf-"& mid(D238,6,3)+1 &"/1" -> CVDf-409/1 | E239: ="redni broj od kardinalnog broja " & substitute(C239,".","") -> redni broj od kardinalnog broja 1107 | H239: Cvetana | I239: S | J239: =len(E239) -> 36 | K239: =D239&C239 -> CVDf-409/11107. | L239: =ifna(VLOOKUP(K239,'Лист1'!D:E,2,false))
A240: RN | B240: ADJ | C240: 1152. | D240: ="CVDf-"& mid(D239,6,3)+1 &"/1" -> CVDf-410/1 | E240: ="redni broj od kardinalnog broja " & substitute(C240,".","") -> redni broj od kardinalnog broja 1152 | H240: Cvetana | I240: S | J240: =len(E240) -> 36 | K240: =D240&C240 -> CVDf-410/11152. | L240: =ifna(VLOOKUP(K240,'Лист1'!D:E,2,false))
... A445: RN | B445: ADJ | C445: 312. | D445: ="CVDf-"& mid(D444,6,3)+1 &"/1" -> CVDf-615/1 | E445: ="redni broj od kardinalnog broja " & substitute(C445,".","") -> redni broj od kardinalnog broja 312 | H445: Cvetana | I445: S | J445: =len(E445) -> 35 | K445: =D445&C445 -> CVDf-615/1312. | L445: =ifna(VLOOKUP(K445,'Лист1'!D:E,2,false))
A446: A | B446: ADJ | C446: 32-bitni | D446: ="CVDf-"& mid(D445,6,3)+1 &"/1" -> CVDf-616/1 | E446: koji ima 32 bita | H446: Cvetana | I446: S | J446: =len(E446) -> 16 | K446: =D446&C446 -> CVDf-616/132-bitni | L446: =ifna(VLOOKUP(K446,'Лист1'!D:E,2,false))
A447: RN | B447: ADJ | C447: 362. | D447: ="CVDf-"& mid(D446,6,3)+1 &"/1" -> CVDf-617/1 | E447: ="redni broj od kardinalnog broja " & substitute(C447,".","") -> redni broj od kardinalnog broja 362 | H447: Cvetana | I447: S | J447: =len(E447) -> 35 | K447: =D447&C447 -> CVDf-617/1362. | L447: =ifna(VLOOKUP(K447,'Лист1'!D:E,2,false))
A448: A | B448: ADJ | C448: 36-godišnji | D448: ="CVDf-"& mid(D447,6,3)+1 &"/1" -> CVDf-618/1 | E448: koji ima 36 godina | H448: Cvetana | I448: S | J448: =len(E448) -> 18 | K448: =D448&C448 -> CVDf-618/136-godišnji | L448: =ifna(VLOOKUP(K448,'Лист1'!D:E,2,false))
A449: RN | B449: ADJ | C449: 4. | D449: ="CVDf-"& mid(D448,6,3)+1 &"/1" -> CVDf-619/1 | E449: ="redni broj od kardinalnog broja " & substitute(C449,".","") -> redni broj od kardinalnog broja 4 | H449: Cvetana | I449: S | J449: =len(E449) -> 33 | K449: =D449&C449 -> CVDf-619/14. | L449: =ifna(VLOOKUP(K449,'Лист1'!D:E,2,false))
A450: RN | B450: ADJ | C450: 430. | D450: ="CVDf-"& mid(D449,6,3)+1 &"/1" -> CVDf-620/1 | E450: ="redni broj od kardinalnog broja " & substitute(C450,".","") -> redni broj od kardinalnog broja 430 | H450: Cvetana | I450: S | J450: =len(E450) -> 35 | K450: =D450&C450 -> CVDf-620/1430. | L450: =ifna(VLOOKUP(K450,'Лист1'!D:E,2,false))
A451: RN | B451: ADJ | C451: 447. | D451: ="CVDf-"& mid(D450,6,3)+1 &"/1" -> CVDf-621/1 | E451: ="redni broj od kardinalnog broja " & substitute(C451,".","") -> redni broj od kardinalnog broja 447 | H451: Cvetana | I451: S | J451: =len(E451) -> 35 | K451: =D451&C451 -> CVDf-621/1447. | L451: =ifna(VLOOKUP(K451,'Лист1'!D:E,2,false))
A452: RN | B452: ADJ | C452: 460 | D452: ="CVDf-"& mid(D451,6,3)+1 &"/1" -> CVDf-622/1 | E452: ="redni broj od kardinalnog broja " & substitute(C452,".","") -> redni broj od kardinalnog broja 460 | H452: Cvetana | I452: S | J452: =len(E452) -> 35 | K452: =D452&C452 -> CVDf-622/1460 | L452: =ifna(VLOOKUP(K452,'Лист1'!D:E,2,false))
A453: N | B453: NOUN | C453: tirozin | D453: ="CVDf-"& mid(D450,6,3)+1 &"/1" -> CVDf-621/1 | E453: neesencijalna aminokiselina koju telo sintetizuje iz druge aminokiseline zvane fenilalanin | F453: tirozin ; 4-hidroksifenilalanin ; L-tirozin | H453: Cvetana | I453: S | J453: =len(E453) -> 90 | K453: =D453&C453 -> CVDf-621/1tirozin | L453: =ifna(VLOOKUP(K453,'Лист1'!D:E,2,false))
A454: N | B454: NOUN | C454: 4-hidroksifenilalanin | D454: ="CVDf-"& mid(D451,6,3)+1 &"/1" -> CVDf-622/1 | E454: neesencijalna aminokiselina koju telo sintetizuje iz druge aminokiseline zvane fenilalanin | F454: tirozin ; 4-hidroksifenilalanin ; L-tirozin | H454: Cvetana | I454: S | J454: =len(E454) -> 90 | K454: =D454&C454 -> CVDf-622/14-hidroksifenilalanin | L454: =ifna(VLOOKUP(K454,'Лист1'!D:E,2,false))
A455: N | B455: NOUN | C455: L-tirozin | D455: ="CVDf-"& mid(D452,6,3)+1 &"/1" -> CVDf-623/1 | E455: neesencijalna aminokiselina koju telo sintetizuje iz druge aminokiseline zvane fenilalanin | F455: tirozin ; 4-hidroksifenilalanin ; L-tirozin | H455: Cvetana | I455: S | J455: =len(E455) -> 90 | K455: =D455&C455 -> CVDf-623/1L-tirozin | L455: =ifna(VLOOKUP(K455,'Лист1'!D:E,2,false))
A456: RN | B456: ADJ | C456: 5. | D456: ="CVDf-"& mid(D455,6,3)+1 &"/1" -> CVDf-624/1 | E456: ="redni broj od kardinalnog broja " & substitute(C456,".","") -> redni broj od kardinalnog broja 5 | H456: Cvetana | I456: S | J456: =len(E456) -> 33 | K456: =D456&C456 -> CVDf-624/15. | L456: =ifna(VLOOKUP(K456,'Лист1'!D:E,2,false))
A457: RN | B457: ADJ | C457: 572. | D457: ="CVDf-"& mid(D456,6,3)+1 &"/1" -> CVDf-625/1 | E457: ="redni broj od kardinalnog broja " & substitute(C457,".","") -> redni broj od kardinalnog broja 572 | H457: Cvetana | I457: S | J457: =len(E457) -> 35 | K457: =D457&C457 -> CVDf-625/1572. | L457: =ifna(VLOOKUP(K457,'Лист1'!D:E,2,false))
A458: RN | B458: ADJ | C458: 58. | D458: ="CVDf-"& mid(D457,6,3)+1 &"/1" -> CVDf-626/1 | E458: ="redni broj od kardinalnog broja " & substitute(C458,".","") -> redni broj od kardinalnog broja 58 | H458: Cvetana | I458: S | J458: =len(E458) -> 34 | K458: =D458&C458 -> CVDf-626/158. | L458: =ifna(VLOOKUP(K458,'Лист1'!D:E,2,false))
A459: RN | B459: ADJ | C459: 65. | D459: ="CVDf-"& mid(D458,6,3)+1 &"/1" -> CVDf-627/1 | E459: ="redni broj od kardinalnog broja " & substitute(C459,".","") -> redni broj od kardinalnog broja 65 | H459: Cvetana | I459: S | J459: =len(E459) -> 34 | K459: =D459&C459 -> CVDf-627/165. | L459: =ifna(VLOOKUP(K459,'Лист1'!D:E,2,false))
A460: RN | B460: ADJ | C460: 680. | D460: ="CVDf-"& mid(D459,6,3)+1 &"/1" -> CVDf-628/1 | E460: ="redni broj od kardinalnog broja " & substitute(C460,".","") -> redni broj od kardinalnog broja 680 | H460: Cvetana | I460: S | J460: =len(E460) -> 35 | K460: =D460&C460 -> CVDf-628/1680. | L460: =ifna(VLOOKUP(K460,'Лист1'!D:E,2,false))
A461: RN | B461: ADJ | C461: 70. | D461: ="CVDf-"& mid(D460,6,3)+1 &"/1" -> CVDf-629/1 | E461: ="redni broj od kardinalnog broja " & substitute(C461,".","") -> redni broj od kardinalnog broja 70 | H461: Cvetana | I461: S | J461: =len(E461) -> 34 | K461: =D461&C461 -> CVDf-629/170. | L461: =ifna(VLOOKUP(K461,'Лист1'!D:E,2,false))
A462: RN | B462: ADJ | C462: 731. | D462: ="CVDf-"& mid(D461,6,3)+1 &"/1" -> CVDf-630/1 | E462: ="redni broj od kardinalnog broja " & substitute(C462,".","") -> redni broj od kardinalnog broja 731 | H462: Cvetana | I462: S | J462: =len(E462) -> 35 | K462: =D462&C462 -> CVDf-630/1731. | L462: =ifna(VLOOKUP(K462,'Лист1'!D:E,2,false))
A463: RN | B463: ADJ | C463: 777. | D463: ="CVDf-"& mid(D462,6,3)+1 &"/1" -> CVDf-631/1 | E463: ="redni broj od kardinalnog broja " & substitute(C463,".","") -> redni broj od kardinalnog broja 777 | H463: Cvetana | I463: S | J463: =len(E463) -> 35 | K463: =D463&C463 -> CVDf-631/1777. | L463: =ifna(VLOOKUP(K463,'Лист1'!D:E,2,false))
A464: RN | B464: ADJ | C464: 796. | D464: ="CVDf-"& mid(D463,6,3)+1 &"/1" -> CVDf-632/1 | E464: ="redni broj od kardinalnog broja " & substitute(C464,".","") -> redni broj od kardinalnog broja 796 | H464: Cvetana | I464: S | J464: =len(E464) -> 35 | K464: =D464&C464 -> CVDf-632/1796. | L464: =ifna(VLOOKUP(K464,'Лист1'!D:E,2,false))
A465: RN | B465: ADJ | C465: 804. | D465: ="CVDf-"& mid(D464,6,3)+1 &"/1" -> CVDf-633/1 | E465: ="redni broj od kardinalnog broja " & substitute(C465,".","") -> redni broj od kardinalnog broja 804 | H465: Cvetana | I465: S | J465: =len(E465) -> 35 | K465: =D465&C465 -> CVDf-633/1804. | L465: =ifna(VLOOKUP(K465,'Лист1'!D:E,2,false))
A466: RN | B466: ADJ | C466: 814. | D466: ="CVDf-"& mid(D465,6,3)+1 &"/1" -> CVDf-634/1 | E466: ="redni broj od kardinalnog broja " & substitute(C466,".","") -> redni broj od kardinalnog broja 814 | H466: Cvetana | I466: S | J466: =len(E466) -> 35 | K466: =D466&C466 -> CVDf-634/1814. | L466: =ifna(VLOOKUP(K466,'Лист1'!D:E,2,false))
A467: RN | B467: ADJ | C467: 857. | D467: ="CVDf-"& mid(D466,6,3)+1 &"/1" -> CVDf-635/1 | E467: ="redni broj od kardinalnog broja " & substitute(C467,".","") -> redni broj od kardinalnog broja 857 | H467: Cvetana | I467: S | J467: =len(E467) -> 35 | K467: =D467&C467 -> CVDf-635/1857. | L467: =ifna(VLOOKUP(K467,'Лист1'!D:E,2,false))
... A473: RN | B473: ADJ | C473: 944. | D473: ="CVDf-"& mid(D472,6,3)+1 &"/1" -> CVDf-641/1 | E473: ="redni broj od kardinalnog broja " & substitute(C473,".","") -> redni broj od kardinalnog broja 944 | H473: Cvetana | I473: S | J473: =len(E473) -> 35 | K473: =D473&C473 -> CVDf-641/1944. | L473: =ifna(VLOOKUP(K473,'Лист1'!D:E,2,false))
A474: V | B474: VERB | C474: igrati ulogu | D474: CVMWE-0001 | E474: (iz)vršiti uticaj, doprineti/doprinositi nečemu | F474: odigrati ulogu;igrati ulogu | H474: CvetanaMWE | I474: VID | J474: =len(E474) -> 47 | K474: =D474&C474 -> CVMWE-0001igrati ulogu | L474: =ifna(VLOOKUP(K474,'Лист1'!D:E,2,false))
A475: V | B475: VERB | C475: odigrati ulogu | D475: CVMWE-0001 | E475: (iz)vršiti uticaj, doprineti/doprinositi nečemu | F475: odigrati ulogu;igrati ulogu | H475: CvetanaMWE | I475: VID | J475: =len(E475) -> 47 | K475: =D475&C475 -> CVMWE-0001odigrati ulogu | L475: =ifna(VLOOKUP(K475,'Лист1'!D:E,2,false))
A476: N | B476: NOUN | C476: akutni napad | D476: CVMWE-0002 | E476: iznenadno pogoršanje bolesti koje zahteva brzu intervenciju ili hospitalizaciju | F476: akutni napad | H476: CvetanaMWE | I476: NID | J476: =len(E476) -> 79 | K476: =D476&C476 -> CVMWE-0002akutni napad | L476: =ifna(VLOOKUP(K476,'Лист1'!D:E,2,false))
A477: N | B477: NOUN | C477: alkalni metal | D477: CVMWE-0003 | E477: metal iz grupe metala sličnih osobina koju čine: litijum, natrijum, kalijum, rubidijum, cezijum i francijum | F477: alkalni metal | H477: CvetanaMWE | I477: NID | J477: =len(E477) -> 107 | K477: =D477&C477 -> CVMWE-0003alkalni metal | L477: =ifna(VLOOKUP(K477,'Лист1'!D:E,2,false))
A478: N | B478: NOUN | C478: apstraktna algebra | D478: CVMWE-0004 | E478: proučavanje algebarskih struktura, koje čine skupovi sa specifičnim operacijama koje deluju na njihove elemente | F478: apstraktna algebra | H478: CvetanaMWE | I478: NID | J478: =len(E478) -> 111 | K478: =D478&C478 -> CVMWE-0004apstraktna algebra | L478: =ifna(VLOOKUP(K478,'Лист1'!D:E,2,false))
A479: N | B479: NOUN | C479: aspiraciona pneumonija | D479: CVMWE-0005 | E479: infekcija uzrokovana udisanjem nečeg drugog osim vazduha u pluća. | F479: aspiraciona pneumonija | H479: CvetanaMWE | I479: NID | J479: =len(E479) -> 66 | K479: =D479&C479 -> CVMWE-0005aspiraciona pneumonija | L479: =ifna(VLOOKUP(K479,'Лист1'!D:E,2,false))
A480: N | B480: NOUN | C480: asteroidni pojas | D480: CVMWE-0006 | E480: region u obliku torusa u Sunčevom sistemu, sa centrom na Suncu koji obuhvata otprilike prostor između orbita planeta Jupitera i Marsa i sadrži veliki broj čvrstih tela nepravilnog oblika zvanih asteroidi ili male planete. | F480: asteroidni pojas | H480: CvetanaMWE | I480: NID | J480: =len(E480) -> 221 | K480: =D480&C480 -> CVMWE-0006asteroidni pojas | L480: =ifna(VLOOKUP(K480,'Лист1'!D:E,2,false))
A481: N | B481: NOUN | C481: atomski radijus | D481: CVMWE-0007 | E481: rastojanje između najudaljenijih elektrona koji se javljaju u određenom atomu i jezgra tog atoma | F481: atomski radijus | H481: CvetanaMWE | J481: =len(E481) -> 96 | K481: =D481&C481 -> CVMWE-0007atomski radijus | L481: =ifna(VLOOKUP(K481,'Лист1'!D:E,2,false))
A482: N | B482: NOUN | C482: avanzirani potencijal | D482: CVMWE-0008 | E482: rešenje talasne jednačine koje zavisi od budućih vrednosti izvora. U formalnom smislu, to je deo rešenja D’Alambertove ili talasne jednačine. | F482: avanzirani potencijal | H482: CvetanaMWE | J482: =len(E482) -> 141 | K482: =D482&C482 -> CVMWE-0008avanzirani potencijal | L482: =ifna(VLOOKUP(K482,'Лист1'!D:E,2,false))
A483: N | B483: NOUN | C483: bakterijska kultura | D483: CVMWE-0009 | E483: metoda za dijagnosticiranje zaraznih bolesti i određivanje načina lečenja | F483: bakterijska kultura | H483: CvetanaMWE | I483: NID | J483: =len(E483) -> 73 | K483: =D483&C483 -> CVMWE-0009bakterijska kultura | L483: =ifna(VLOOKUP(K483,'Лист1'!D:E,2,false))
A484: N | B484: NOUN | C484: bar-kod | D484: CVMWE-0010 | E484: metod predstavljanja podataka u vizuelnom, mašinski čitljivom obliku pomoću uskih i debelih pruga | F484: prugasti kod;bar-kod | H484: CvetanaMWE | I484: NID | J484: =len(E484) -> 97 | K484: =D484&C484 -> CVMWE-0010bar-kod | L484: =ifna(VLOOKUP(K484,'Лист1'!D:E,2,false))
A485: N | B485: NOUN | C485: prugasti kod | D485: CVMWE-0010 | E485: metod predstavljanja podataka u vizuelnom, mašinski čitljivom obliku pomoću uskih i debelih pruga | F485: prugasti kod;bar-kod | H485: CvetanaMWE | J485: =len(E485) -> 97 | K485: =D485&C485 -> CVMWE-0010prugasti kod | L485: =ifna(VLOOKUP(K485,'Лист1'!D:E,2,false))
A486: V | B486: VERB | C486: baviti se | D486: CVMWE-0011 | E486: zanimati se nečim, raditi, poslovati nešto | F486: baviti se | H486: CvetanaMWE | I486: IRV | J486: =len(E486) -> 42 | K486: =D486&C486 -> CVMWE-0011baviti se | L486: =ifna(VLOOKUP(K486,'Лист1'!D:E,2,false))
A487: V | B487: VERB | C487: baviti se | D487: CVMWE-0012 | E487: obrađivati nešto kao temu knjige, filma i sl. | F487: baviti se | H487: CvetanaMWE | I487: IRV | J487: =len(E487) -> 45 | K487: =D487&C487 -> CVMWE-0012baviti se | L487: =ifna(VLOOKUP(K487,'Лист1'!D:E,2,false))
A488: V | B488: VERB | C488: baviti se | D488: CVMWE-0013 | E488: proučavati nešto, imati nešto za predmet proučavanja | F488: baviti se | H488: CvetanaMWE | I488: IRV | J488: =len(E488) -> 52 | K488: =D488&C488 -> CVMWE-0013baviti se | L488: =ifna(VLOOKUP(K488,'Лист1'!D:E,2,false))
A489: N | B489: NOUN | C489: berilijum fluorid | D489: CVMWE-0014 | E489: neorgansko jedinjenje sa formulom BeF2 | F489: berilijum fluorid | H489: CvetanaMWE | I489: NID | J489: =len(E489) -> 38 | K489: =D489&C489 -> CVMWE-0014berilijum fluorid | L489: =ifna(VLOOKUP(K489,'Лист1'!D:E,2,false))
A490: N | B490: NOUN | C490: berilijum hlorid | D490: CVMWE-0015 | E490: neorgansko jedinjenje sa formulom BeCl2 | F490: berilijum hlorid | H490: CvetanaMWE | I490: NID | J490: =len(E490) -> 39 | K490: =D490&C490 -> CVMWE-0015berilijum hlorid | L490: =ifna(VLOOKUP(K490,'Лист1'!D:E,2,false))
A491: ADV | B491: ADV | C491: bez izlaza na more | D491: CVMWE-0016 | E491: o zemljama koje nemaju direktan pristup okeanu ili moru koje nije u potpunosti okruženo kopnom | F491: bez izlaza na more | H491: CvetanaMWE | I491: AdvID | J491: =len(E491) -> 94 | K491: =D491&C491 -> CVMWE-0016bez izlaza na more | L491: =ifna(VLOOKUP(K491,'Лист1'!D:E,2,false))
A492: ADV | B492: ADV | C492: bez premca | D492: CVMWE-0017 | E492: neko ili nešto čemu nema ravnog | F492: bez premca | H492: CvetanaMWE | I492: AdvID | J492: =len(E492) -> 31 | K492: =D492&C492 -> CVMWE-0017bez premca | L492: =ifna(VLOOKUP(K492,'Лист1'!D:E,2,false))
A493: N | B493: NOUN | C493: Bezjeova površ | D493: CVMWE-0018 | E493: vrsta matematičkog splajna koji se koristi u računarskojgrafici, računarski potpomognutom dizajnu i modeliranju metodama konačnih elemenata | F493: Bezjeova površ | H493: CvetanaMWE | I493: NID | J493: =len(E493) -> 139 | K493: =D493&C493 -> CVMWE-0018Bezjeova površ | L493: =ifna(VLOOKUP(K493,'Лист1'!D:E,2,false))
A494: N | B494: NOUN | C494: biološka nauka | D494: CVMWE-0019 | E494: proučavanje živih bića i njihovog delovanja; kako se živi organizmi, kao što su životinje, biljke i bakterije, prilagođavaju, evoluiraju i napreduju | F494: biološka nauka | H494: CvetanaMWE | I494: NID | J494: =len(E494) -> 149 | K494: =D494&C494 -> CVMWE-0019biološka nauka | L494: =ifna(VLOOKUP(K494,'Лист1'!D:E,2,false))
A495: N | B495: NOUN | C495: Birklandova struja | D495: CVMWE-0020 | E495: skup električnih struja koje teku duž linija geomagnetnog polja koje povezuju Zemljinu magnetosferu sa jonosferom velike geografske širine Zemlje | F495: Birklandova struja | H495: CvetanaMWE | J495: =len(E495) -> 145 | K495: =D495&C495 -> CVMWE-0020Birklandova struja | L495: =ifna(VLOOKUP(K495,'Лист1'!D:E,2,false))
A496: V | B496: VERB | C496: biti na ceni | D496: CVMWE-0021 | E496: biti cenjen, uvažavan | F496: biti na ceni | H496: CvetanaMWE | I496: VID | J496: =len(E496) -> 21 | K496: =D496&C496 -> CVMWE-0021biti na ceni | L496: =ifna(VLOOKUP(K496,'Лист1'!D:E,2,false))
A497: V | B497: VERB | C497: biti u <nečijim> rukama | D497: CVMWE-0022 | E497: biti u nečijoj vlasti | F497: biti u <nečijim> rukama | H497: CvetanaMWE | I497: VID | J497: =len(E497) -> 21 | K497: =D497&C497 -> CVMWE-0022biti u <nečijim> rukama | L497: =ifna(VLOOKUP(K497,'Лист1'!D:E,2,false))
A498: N | B498: NOUN | C498: bizmut subsalicilat | D498: CVMWE-0023 | E498: lek koji se koristi za lečenje privremene nelagodnosti u stomaku i gastrointestinalnom traktu | F498: bizmut subsalicilat | H498: CvetanaMWE | I498: NID | J498: =len(E498) -> 93 | K498: =D498&C498 -> CVMWE-0023bizmut subsalicilat | L498: =ifna(VLOOKUP(K498,'Лист1'!D:E,2,false))
A499: V | B499: VERB | C499: bližiti se | D499: CVMWE-0024 | E499: približavati, primicati se vremenski ili prostorno | F499: bližiti se | H499: CvetanaMWE | I499: IRV | J499: =len(E499) -> 50 | K499: =D499&C499 -> CVMWE-0024bližiti se | L499: =ifna(VLOOKUP(K499,'Лист1'!D:E,2,false))
A500: V | B500: VERB | C500: bojati se | D500: CVMWE-0025 | E500: ne usuđivati se uraditi nešto iz straha | F500: bojati se | H500: CvetanaMWE | I500: IRV | J500: =len(E500) -> 39 | K500: =D500&C500 -> CVMWE-0025bojati se | L500: =ifna(VLOOKUP(K500,'Лист1'!D:E,2,false))
A501: N | B501: NOUN | C501: bojni brod | D501: CVMWE-0026 | E501: veliki, teško oklopljeni ratni brod sa glavnom baterijom koja se sastoji od topova velikog kalibra, dizajniranih da služe kao glavni brodovi sa najintenzivnijom vatrenom moći | F501: bojni brod | H501: CvetanaMWE | I501: NID | J501: =len(E501) -> 175 | K501: =D501&C501 -> CVMWE-0026bojni brod | L501: =ifna(VLOOKUP(K501,'Лист1'!D:E,2,false))
A502: N | B502: NOUN | C502: bombaš samoubica | D502: CVMWE-0027 | E502: osoba, posebno terorista, koja izvršava bombaški napad sa namerom da uz druge ljude ubije i sebe | F502: bombaš samoubica | H502: CvetanaMWE | I502: NID | J502: =len(E502) -> 96 | K502: =D502&C502 -> CVMWE-0027bombaš samoubica | L502: =ifna(VLOOKUP(K502,'Лист1'!D:E,2,false))
A503: V | B503: VERB | C503: boriti se | D503: CVMWE-0028 | E503: voditi oružanu borbu, učestvovati u oružanoj borbi | F503: boriti se | H503: CvetanaMWE | I503: IRV | J503: =len(E503) -> 50 | K503: =D503&C503 -> CVMWE-0028boriti se | L503: =ifna(VLOOKUP(K503,'Лист1'!D:E,2,false))
A504: N | B504: NOUN | C504: aqua regia | D504: CVMWE-0029 | E504: mešavina azotne i hlorovodonične kiseline, optimalno u molskom odnosu 1:3 | F504: carska voda;aqua regia | H504: CvetanaMWE | I504: NID | J504: =len(E504) -> 73 | K504: =D504&C504 -> CVMWE-0029aqua regia | L504: =ifna(VLOOKUP(K504,'Лист1'!D:E,2,false))
A505: N | B505: NOUN | C505: carska voda | D505: CVMWE-0029 | E505: mešavina azotne i hlorovodonične kiseline, optimalno u molskom odnosu 1:3 | F505: carska voda;aqua regia | H505: CvetanaMWE | I505: NID | J505: =len(E505) -> 73 | K505: =D505&C505 -> CVMWE-0029carska voda | L505: =ifna(VLOOKUP(K505,'Лист1'!D:E,2,false))
A506: N | B506: NOUN | C506: ćelijska deoba | D506: CVMWE-0030 | E506: proces kojim se roditeljska ćelija deli na dve ćerke ćelije | F506: ćelijska deoba | H506: CvetanaMWE | J506: =len(E506) -> 62 | K506: =D506&C506 -> CVMWE-0030ćelijska deoba | L506: =ifna(VLOOKUP(K506,'Лист1'!D:E,2,false))
A507: N | B507: NOUN | C507: ćelijska smrt | D507: CVMWE-0031 | E507: događaj prestanka biološke ćelije da obavlja svoje funkcije | F507: ćelijska smrt | H507: CvetanaMWE | I507: NID | J507: =len(E507) -> 60 | K507: =D507&C507 -> CVMWE-0031ćelijska smrt | L507: =ifna(VLOOKUP(K507,'Лист1'!D:E,2,false))
A508: N | B508: NOUN | C508: celoživotno učenje | D508: CVMWE-0032 | E508: kontinuirano sticanje znanja po završetku formalnog obrazovanja | F508: celoživotno učenje | H508: CvetanaMWE | J508: =len(E508) -> 63 | K508: =D508&C508 -> CVMWE-0032celoživotno učenje | L508: =ifna(VLOOKUP(K508,'Лист1'!D:E,2,false))
A509: V | B509: VERB | C509: činiti se | D509: CVMWE-0033 | E509: izgleda da nešto važi premda nije sigurno | F509: činiti se | H509: CvetanaMWE | I509: IRV | J509: =len(E509) -> 41 | K509: =D509&C509 -> CVMWE-0033činiti se | L509: =ifna(VLOOKUP(K509,'Лист1'!D:E,2,false))
A510: V | B510: VERB | C510: činiti većinu | D510: CVMWE-0034 | E510: sačinjavati, tvoriti veći deo u nekom skupu | F510: činiti većinu | H510: CvetanaMWE | I510: VID | J510: =len(E510) -> 43 | K510: =D510&C510 -> CVMWE-0034činiti većinu | L510: =ifna(VLOOKUP(K510,'Лист1'!D:E,2,false))
A511: N | B511: NOUN | C511: CT pregled | D511: CVMWE-0035 | E511: radiološki je metod snimanja koji pored rendgen zračenja primenjuje i tomografiju | F511: CT pregled;kompjuterizovana tomografija | H511: CvetanaMWE | I511: NID | J511: =len(E511) -> 81 | K511: =D511&C511 -> CVMWE-0035CT pregled | L511: =ifna(VLOOKUP(K511,'Лист1'!D:E,2,false))
A512: N | B512: NOUN | C512: kompjuterizovana tomografija | D512: CVMWE-0035 | E512: radiološki je metod snimanja koji pored rendgen zračenja primenjuje i tomografiju | F512: CT pregled;kompjuterizovana tomografija | H512: CvetanaMWE | J512: =len(E512) -> 81 | K512: =D512&C512 -> CVMWE-0035kompjuterizovana tomografija | L512: =ifna(VLOOKUP(K512,'Лист1'!D:E,2,false))
A513: N | B513: NOUN | C513: čvrsta materija | D513: CVMWE-0036 | E513: materija u jednom od četiri osnovna stanja materije (ostala su ečnost, gas i plazma) | F513: čvrsta materija | H513: CvetanaMWE | I513: NID | J513: =len(E513) -> 84 | K513: =D513&C513 -> CVMWE-0036čvrsta materija | L513: =ifna(VLOOKUP(K513,'Лист1'!D:E,2,false))
A514: N | B514: NOUN | C514: Daning—Krugerov efekat | D514: CVMWE-0037 | E514: kognitivna pristrasnost zbog koje ljudi sa ograničenom kompetencijom u određenom domenu precenjuju svoje sposobnosti | F514: Daning—Krugerov efekat | H514: CvetanaMWE | J514: =len(E514) -> 116 | K514: =D514&C514 -> CVMWE-0037Daning—Krugerov efekat | L514: =ifna(VLOOKUP(K514,'Лист1'!D:E,2,false))
A515: V | B515: VERB | C515: dati doprinos | D515: CVMWE-0038 | E515: doprineti | F515: dati doprinos | H515: CvetanaMWE | I515: LVC.full | J515: =len(E515) -> 9 | K515: =D515&C515 -> CVMWE-0038dati doprinos | L515: =ifna(VLOOKUP(K515,'Лист1'!D:E,2,false))
A516: V | B516: VERB | C516: dati ocenu | D516: CVMWE-0039 | E516: oceniti nekoga ili nešro, proceniti prednost nekoge ili nečega | F516: dati ocenu | H516: CvetanaMWE | I516: LVC.full | J516: =len(E516) -> 62 | K516: =D516&C516 -> CVMWE-0039dati ocenu | L516: =ifna(VLOOKUP(K516,'Лист1'!D:E,2,false))
A517: V | B517: VERB | C517: dati ostavku | D517: CVMWE-0040 | E517: pismenim ili usmenim putem osoba izjavljuje da se odriče svoje, funkcije, položaja te da prestaja da obavlja poslove i dužnosti | F517: dati ostavku | H517: CvetanaMWE | I517: LVC.full | J517: =len(E517) -> 127 | K517: =D517&C517 -> CVMWE-0040dati ostavku | L517: =ifna(VLOOKUP(K517,'Лист1'!D:E,2,false))
A518: V | B518: VERB | C518: dati pravo | D518: CVMWE-0041 | E518: odobriti nekome da nešto radi, deluje na neki način | F518: dati pravo | H518: CvetanaMWE | I518: LVC.full | J518: =len(E518) -> 51 | K518: =D518&C518 -> CVMWE-0041dati pravo | L518: =ifna(VLOOKUP(K518,'Лист1'!D:E,2,false))
A519: V | B519: VERB | C519: dati boju | D519: CVMWE-0042 | E519: biti uzrok nastanka ili postojanja boje nečega | F519: dati boju;davati boju | H519: CvetanaMWE | I519: VID | J519: =len(E519) -> 46 | K519: =D519&C519 -> CVMWE-0042dati boju | L519: =ifna(VLOOKUP(K519,'Лист1'!D:E,2,false))
A520: V | B520: VERB | C520: davati boju | D520: CVMWE-0042 | E520: biti uzrok nastanka ili postojanja boje nečega | F520: dati boju;davati boju | H520: CvetanaMWE | I520: VID | J520: =len(E520) -> 46 | K520: =D520&C520 -> CVMWE-0042davati boju | L520: =ifna(VLOOKUP(K520,'Лист1'!D:E,2,false))
A521: V | B521: VERB | C521: dati donaciju | D521: CVMWE-0043 | E521: donirati | F521: dati donaciju;davati donaciju | H521: CvetanaMWE | I521: LVC.full | J521: =len(E521) -> 8 | K521: =D521&C521 -> CVMWE-0043dati donaciju | L521: =ifna(VLOOKUP(K521,'Лист1'!D:E,2,false))
A522: V | B522: VERB | C522: davati donaciju | D522: CVMWE-0043 | E522: donirati | F522: dati donaciju;davati donaciju | H522: CvetanaMWE | I522: LVC.full | J522: =len(E522) -> 8 | K522: =D522&C522 -> CVMWE-0043davati donaciju | L522: =ifna(VLOOKUP(K522,'Лист1'!D:E,2,false))
...

Sheet Лист2
A1: Sense_Entity_Lemma | B1: provera | C1: imaih | D1: Ima veliko slovo
A2: agencija | B2: =VLOOKUP(A2,Sheet1!C:H,6,false) -> SrpWN | C2: =countif(Sheet1!C:C,"="&A2) -> 2 | D2: =AND(CODE(LEFT(A2,1))>=65, CODE(LEFT(A2,1))<=90) -> FALSE
A3: akcija | B3: =VLOOKUP(A3,Sheet1!C:H,6,false) -> SrpWN | C3: =countif(Sheet1!C:C,"="&A3) -> 9 | D3: =AND(CODE(LEFT(A3,1))>=65, CODE(LEFT(A3,1))<=90) -> FALSE
A4: aktuelan | B4: =VLOOKUP(A4,Sheet1!C:H,6,false) -> SrpWN | C4: =countif(Sheet1!C:C,"="&A4) -> 1 | D4: =AND(CODE(LEFT(A4,1))>=65, CODE(LEFT(A4,1))<=90) -> FALSE
A5: akutan | B5: =VLOOKUP(A5,Sheet1!C:H,6,false) -> SrpWN | C5: =countif(Sheet1!C:C,"="&A5) -> 1 | D5: =AND(CODE(LEFT(A5,1))>=65, CODE(LEFT(A5,1))<=90) -> FALSE
A6: albanski | B6: =VLOOKUP(A6,Sheet1!C:H,6,false) -> SrpWN | C6: =countif(Sheet1!C:C,"="&A6) -> 1 | D6: =AND(CODE(LEFT(A6,1))>=65, CODE(LEFT(A6,1))<=90) -> FALSE
A7: album | B7: =VLOOKUP(A7,Sheet1!C:H,6,false) -> SrpWN | C7: =countif(Sheet1!C:C,"="&A7) -> 2 | D7: =AND(CODE(LEFT(A7,1))>=65, CODE(LEFT(A7,1))<=90) -> FALSE
A8: alkoholni | B8: =VLOOKUP(A8,Sheet1!C:H,6,false) -> SrpWN | C8: =countif(Sheet1!C:C,"="&A8) -> 1 | D8: =AND(CODE(LEFT(A8,1))>=65, CODE(LEFT(A8,1))<=90) -> FALSE
A9: alternativa | B9: =VLOOKUP(A9,Sheet1!C:H,6,false) -> SrpWN | C9: =countif(Sheet1!C:C,"="&A9) -> 1 | D9: =AND(CODE(LEFT(A9,1))>=65, CODE(LEFT(A9,1))<=90) -> FALSE
A10: amandman | B10: =VLOOKUP(A10,Sheet1!C:H,6,false) -> SrpWN | C10: =countif(Sheet1!C:C,"="&A10) -> 1 | D10: =AND(CODE(LEFT(A10,1))>=65, CODE(LEFT(A10,1))<=90) -> FALSE
A11: analiza | B11: =VLOOKUP(A11,Sheet1!C:H,6,false) -> SrpWN | C11: =countif(Sheet1!C:C,"="&A11) -> 3 | D11: =AND(CODE(LEFT(A11,1))>=65, CODE(LEFT(A11,1))<=90) -> FALSE
A12: angažovati | B12: =VLOOKUP(A12,Sheet1!C:H,6,false) -> SrpWN | C12: =countif(Sheet1!C:C,"="&A12) -> 2 | D12: =AND(CODE(LEFT(A12,1))>=65, CODE(LEFT(A12,1))<=90) -> FALSE
A13: anime | B13: =VLOOKUP(A13,Sheet1!C:H,6,false) -> Cvetana | C13: =countif(Sheet1!C:C,"="&A13) -> 1 | D13: =AND(CODE(LEFT(A13,1))>=65, CODE(LEFT(A13,1))<=90) -> FALSE
... A608: životinja | B608: =VLOOKUP(A608,Sheet1!C:H,6,false) -> SrpWN | C608: =countif(Sheet1!C:C,"="&A608) -> 1 | D608: =AND(CODE(LEFT(A608,1))>=65, CODE(LEFT(A608,1))<=90) -> FALSE

Sheet Лист1
A1: UPOS | B1: lemma | C1: senseID | E1: Akcija | F1: literals | G1: definition | H1: Велико слово
A2: ADJ | B2: anoniman | C2: ENG30-00120574-a | D2: =C2&B2 -> ENG30-00120574-aanoniman | E2: dodati | F2: anonimni | G2: čije ile ili identitet nisu poznati | H2: =EXACT(B2, LOWER(B2)) -> TRUE
A3: ADJ | B3: bakaran | C3: ENG30-02707889-a | D3: =C3&B3 -> ENG30-02707889-abakaran | E3: dodati | F3: bakarni | G3: koji je napravljen od bakra ili sadrži bakar | H3: =EXACT(B3, UPPER(B3)) -> FALSE
A4: ADJ | B4: doživotan | C4: ENG30-01440159-a | D4: =C4&B4 -> ENG30-01440159-adoživotan | E4: dodati | F4: doživotni; doživotno; od kolevke do groba | G4: traje kroz život | H4: =EXACT(B4, UPPER(B4)) -> FALSE
A5: ADJ | B5: drevan | C5: ENG30-01644847-a | D5: =C5&B5 -> ENG30-01644847-adrevan | E5: dodati | F5: drevni | G5: onaj koji je veoma star | H5: =EXACT(B5, UPPER(B5)) -> FALSE
A6: ADJ | B6: dvodoman | C6: ENG30-02479361-a | D6: =C6&B6 -> ENG30-02479361-advodoman | E6: dodati | F6: dvodomni; dvokomorni | G6: sastoji se od dve komore | H6: =EXACT(B6, UPPER(B6)) -> FALSE
A7: ADJ | B7: glotalan | C7: ENG30-02880924-a | D7: =C7&B7 -> ENG30-02880924-aglotalan | E7: dodati | F7: glotalni | G7: ili koji se odnosi na ili proizvodi glotis | H7: =EXACT(B7, UPPER(B7)) -> FALSE
A8: ADJ | B8: hibridan | C8: ENG30-01904485-a | D8: =C8&B8 -> ENG30-01904485-ahibridan | E8: dodati | F8: hibridni | G8: koji je nastao ukrštanjem sorti ili vrsta (biljaka ili životinja) | H8: =EXACT(B8, UPPER(B8)) -> FALSE
A9: ADJ | B9: kognitivan | C9: ENG30-02898584-a | D9: =C9&B9 -> ENG30-02898584-akognitivan | E9: dodati | F9: saznajni; kognitivni | G9: Koji je, odnosi se ili uključuje saznanje. | H9: =EXACT(B9, UPPER(B9)) -> FALSE
A10: ADJ | B10: ljubavan | C10: ENG30-01465214-a | D10: =C10&B10 -> ENG30-01465214-aljubavan | E10: dodati | F10: ljubavni; ljubavnički; romantičan | G10: koji izražava ili pobuđuje seksualnu ljubav ili romansu | H10: =EXACT(B10, UPPER(B10)) -> FALSE
A11: ADJ | B11: mentalan | C11: ENG30-01273910-a | D11: =C11&B11 -> ENG30-01273910-amentalan | E11: dodati | F11: duševni; mentalni; subjektivan | G11: mentalni čin koji se u potpunosti odvija u domenu uma | H11: =EXACT(B11, UPPER(B11)) -> FALSE
A12: ADJ | B12: mentalan | C12: ENG30-01779986-a | D12: =C12&B12 -> ENG30-01779986-amentalan | E12: dodati | F12: mentalni; umni | G12: koji uključuje um i intelektualne procese | H12: =EXACT(B12, UPPER(B12)) -> FALSE
A13: ADJ | B13: metalan | C13: ENG30-01527420-a | D13: =C13&B13 -> ENG30-01527420-ametalan | E13: dodati | F13: metal; metalik; metalni | G13: sadrži ili je napravljen od ili liči na metal | H13: =EXACT(B13, UPPER(B13)) -> FALSE
A14: ADJ | B14: monumentalan | C14: ENG30-02163468-a | D14: =C14&B14 -> ENG30-02163468-amonumentalan | E14: dodati | F14: monumentalni; monumentalno | G14: od izuzetnog značaja | H14: =EXACT(B14, UPPER(B14)) -> FALSE
... A122: VERB | B122: nalaziti | C122: ENG30-02731390-v | D122: =C122&B122 -> ENG30-02731390-vnalaziti | E122: briši | F122: naći se; nalaziti se; počivati | G122: zavisiti od nečeg drugog (izrečeno metaforom boravka na određenom mestu) | H122: =EXACT(B122, UPPER(B122)) -> FALSE
